amsdal/manager.pyi
amsdal/__init__.pyi
amsdal/__init__.py
amsdal/manager.cpython-311-darwin.so
amsdal/Third-Party Materials - AMSDAL Dependencies - License Notices.md
amsdal/__about__.py
amsdal/errors.pyi
amsdal/py.typed
amsdal/errors.py
amsdal/__about__.pyi
amsdal/storages/__init__.pyi
amsdal/storages/__init__.py
amsdal/storages/file_system.pyi
amsdal/storages/file_system.py
amsdal/context/manager.pyi
amsdal/context/__init__.pyi
amsdal/context/__init__.py
amsdal/context/manager.py
amsdal/mixins/class_versions_mixin.pyi
amsdal/mixins/__init__.pyi
amsdal/mixins/__init__.cpython-311-darwin.so
amsdal/mixins/class_versions_mixin.cpython-311-darwin.so
amsdal/utils/__init__.pyi
amsdal/utils/contrib_paths.py
amsdal/utils/__init__.py
amsdal/utils/contrib_paths.pyi
amsdal/utils/tests/enums.py
amsdal/utils/tests/__init__.py
amsdal/utils/tests/factories.py
amsdal/utils/tests/migrations.py
amsdal/utils/tests/helpers.py
amsdal/utils/rollback/__init__.pyi
amsdal/utils/rollback/__init__.py
amsdal/models/mixins.py
amsdal/models/__init__.py
amsdal/models/types/object.py
amsdal/models/types/__init__.py
amsdal/models/core/validator.py
amsdal/models/core/fixture.py
amsdal/models/core/option.py
amsdal/models/core/__init__.py
amsdal/models/core/storage_metadata.py
amsdal/models/core/file.py
amsdal/models/core/class_property.py
amsdal/models/core/class_object.py
amsdal/contrib/__init__.pyi
amsdal/contrib/app_config.pyi
amsdal/contrib/__init__.cpython-311-darwin.so
amsdal/contrib/app_config.py
amsdal/contrib/auth/__init__.pyi
amsdal/contrib/auth/__init__.py
amsdal/contrib/auth/settings.pyi
amsdal/contrib/auth/app.pyi
amsdal/contrib/auth/errors.pyi
amsdal/contrib/auth/settings.py
amsdal/contrib/auth/app.py
amsdal/contrib/auth/errors.py
amsdal/contrib/auth/migrations/0001_add_mfa_support.py
amsdal/contrib/auth/migrations/0000_initial.py
amsdal/contrib/auth/decorators/__init__.pyi
amsdal/contrib/auth/decorators/__init__.py
amsdal-0.5.43.dist-info/RECORD
amsdal-0.5.43.dist-info/WHEEL
amsdal-0.5.43.dist-info/top_level.txt
amsdal-0.5.43.dist-info/METADATA
amsdal-0.5.43.dist-info/licenses/LICENSE.txt
