Metadata-Version: 2.4
Name: amsdal
Version: 0.5.43
Summary: AMSDAL
License: AMSDAL End User License Agreement
Project-URL: Documentation, https://pypi.org/project/amsdal/#readme
Project-URL: Issues, https://pypi.org/project/amsdal/
Project-URL: Source, https://pypi.org/project/amsdal/
Classifier: Development Status :: 4 - Beta
Classifier: Programming Language :: Python
Classifier: Programming Language :: Python :: 3.11
Classifier: Programming Language :: Python :: 3.12
Classifier: Programming Language :: Python :: 3.13
Classifier: Programming Language :: Python :: Implementation :: CPython
Classifier: Programming Language :: Python :: Implementation :: PyPy
Requires-Python: <3.14,>=3.11
License-File: LICENSE.txt
Requires-Dist: pydantic~=2.12
Requires-Dist: pydantic-settings~=2.12
Requires-Dist: PyJWT~=2.8
Requires-Dist: cryptography~=42.0
Requires-Dist: httpx~=0.25
Requires-Dist: bcrypt~=4.0
Requires-Dist: pyotp~=2.9
Requires-Dist: black>=24.3.0
Requires-Dist: amsdal_utils==0.5.*
Requires-Dist: amsdal_data>=0.5.8
Requires-Dist: amsdal_models==0.5.*
Requires-Dist: pip>=21.3.1
Provides-Extra: cli
Requires-Dist: amsdal-cli==0.5.*; extra == "cli"
Provides-Extra: server
Requires-Dist: amsdal-server==0.5.*; extra == "server"
Provides-Extra: factory
Requires-Dist: polyfactory==2.*; extra == "factory"
Provides-Extra: celery
Requires-Dist: celery==5.4.0; extra == "celery"
Provides-Extra: async-sqlite
Requires-Dist: amsdal-data[async-sqlite]; extra == "async-sqlite"
Provides-Extra: postgres-binary
Requires-Dist: amsdal-data[postgres-binary]; extra == "postgres-binary"
Provides-Extra: postgres-c
Requires-Dist: amsdal-data[postgres-c]; extra == "postgres-c"
Dynamic: license-file
